conset/__init__.py
conset/console.pyd
conset/console.pyi
conset/extra.py
conset-0.1.4.dist-info/licenses/LICENSE
conset-0.1.4.dist-info/METADATA
conset-0.1.4.dist-info/WHEEL
conset-0.1.4.dist-info/top_level.txt
conset-0.1.4.dist-info/RECORD
